{
  "last_updated": "2026-01-28T21:35:59.970209",
  "total_categories": 6,
  "total_feeds": 36,
  "categories": {
    "environmental_news": {
      "feed_count": 7,
      "feeds": [
        {
          "url": "https://insideclimatenews.org/feed/",
          "status": "success",
          "fetched_at": "2026-01-28T21:36:00.089378"
        },
        {
          "url": "https://www.carbonbrief.org/feed/",
          "status": "success",
          "fetched_at": "2026-01-28T21:36:00.314030"
        },
        {
          "url": "https://www.theguardian.com/environment/climate-crisis/rss",
          "status": "success",
          "fetched_at": "2026-01-28T21:36:00.382498"
        },
        {
          "url": "https://grist.org/feed/",
          "status": "success",
          "fetched_at": "2026-01-28T21:36:00.652121"
        },
        {
          "url": "https://e360.yale.edu/feed/",
          "status": "success",
          "fetched_at": "2026-01-28T21:36:01.067885"
        },
        {
          "url": "https://climatecrisis.house.gov/rss.xml",
          "status": "success",
          "fetched_at": "2026-01-28T21:36:08.552751"
        },
        {
          "url": "https://www.climatechangenews.com/feed/",
          "status": "success",
          "fetched_at": "2026-01-28T21:36:11.050127"
        }
      ],
      "successful_fetches": 7,
      "failed_fetches": 0
    },
    "climate_science": {
      "feed_count": 7,
      "feeds": [
        {
          "url": "https://climate.nasa.gov/feed/",
          "status": "success",
          "fetched_at": "2026-01-28T21:36:12.028016"
        },
        {
          "url": "https://www.ipcc.ch/feed/",
          "status": "success",
          "fetched_at": "2026-01-28T21:36:13.240518"
        },
        {
          "url": "https://www.climate.gov/news-features/feed",
          "status": "success",
          "fetched_at": "2026-01-28T21:36:13.522225"
        },
        {
          "url": "https://www.nature.com/nclimate.rss",
          "status": "success",
          "fetched_at": "2026-01-28T21:36:13.603271"
        },
        {
          "url": "https://www.science.org/rss/news_current.xml",
          "status": "success",
          "fetched_at": "2026-01-28T21:36:13.776581"
        },
        {
          "url": "https://www.sciencedaily.com/rss/earth_climate/climate.xml",
          "status": "success",
          "fetched_at": "2026-01-28T21:36:14.019445"
        },
        {
          "url": "https://unfccc.int/news/rss.xml",
          "status": "success",
          "fetched_at": "2026-01-28T21:36:37.483154"
        }
      ],
      "successful_fetches": 7,
      "failed_fetches": 0
    },
    "research_papers": {
      "feed_count": 7,
      "feeds": [
        {
          "url": "https://www.pnas.org/action/showFeed?type=etoc&feed=rss&jc=pnas",
          "status": "success",
          "fetched_at": "2026-01-28T21:36:37.684449"
        },
        {
          "url": "https://agupubs.onlinelibrary.wiley.com/feed/19448007/most-recent",
          "status": "success",
          "fetched_at": "2026-01-28T21:36:37.880041"
        },
        {
          "url": "https://iopscience.iop.org/journal/rss/1748-9326",
          "status": "success",
          "fetched_at": "2026-01-28T21:36:38.492451"
        },
        {
          "url": "https://www.frontiersin.org/journals/climate/rss",
          "status": "success",
          "fetched_at": "2026-01-28T21:36:39.299539"
        },
        {
          "url": "https://journals.ametsoc.org/action/showFeed?type=etoc&feed=rss&jc=clim",
          "status": "success",
          "fetched_at": "2026-01-28T21:36:39.354776"
        },
        {
          "url": "https://www.nature.com/nclimate.rss",
          "status": "success",
          "fetched_at": "2026-01-28T21:36:39.403319"
        },
        {
          "url": "https://www.sciencedirect.com/journal/global-environmental-change/rss",
          "status": "success",
          "fetched_at": "2026-01-28T21:36:39.646136"
        }
      ],
      "successful_fetches": 7,
      "failed_fetches": 0
    },
    "social_impact": {
      "feed_count": 6,
      "feeds": [
        {
          "url": "https://www.climatemigration.org.uk/rss",
          "status": "success",
          "fetched_at": "2026-01-28T21:36:50.375021"
        },
        {
          "url": "https://ejfoundation.org/rss/climate",
          "status": "success",
          "fetched_at": "2026-01-28T21:36:51.026752"
        },
        {
          "url": "https://www.climaterealityproject.org/blog/rss.xml",
          "status": "success",
          "fetched_at": "2026-01-28T21:36:51.439562"
        },
        {
          "url": "https://www.wri.org/blog/rss.xml",
          "status": "success",
          "fetched_at": "2026-01-28T21:36:51.998771"
        },
        {
          "url": "https://www.sei.org/feed/",
          "status": "success",
          "fetched_at": "2026-01-28T21:36:53.965163"
        },
        {
          "url": "https://www.climatejusticealliance.org/feed/",
          "status": "success",
          "fetched_at": "2026-01-28T21:36:54.755591"
        }
      ],
      "successful_fetches": 6,
      "failed_fetches": 0
    },
    "extreme_weather": {
      "feed_count": 5,
      "feeds": [
        {
          "url": "https://www.wunderground.com/cat6/feed",
          "status": "success",
          "fetched_at": "2026-01-28T21:36:55.311394"
        },
        {
          "url": "https://www.climatesignals.org/rss.xml",
          "status": "success",
          "fetched_at": "2026-01-28T21:36:56.608339"
        },
        {
          "url": "https://www.preventionweb.net/english/professional/news/rss.php",
          "status": "success",
          "fetched_at": "2026-01-28T21:36:57.214708"
        },
        {
          "url": "https://phys.org/rss-feed/earth-sciences/earth-sciences-news/",
          "status": "success",
          "fetched_at": "2026-01-28T21:36:57.500994"
        },
        {
          "url": "https://floodlist.com/feed",
          "status": "success",
          "fetched_at": "2026-01-28T21:36:57.710508"
        }
      ],
      "successful_fetches": 5,
      "failed_fetches": 0
    },
    "media": {
      "feed_count": 4,
      "feeds": [
        {
          "url": "https://climatecrisis.house.gov/rss.xml",
          "status": "success",
          "fetched_at": "2026-01-28T21:36:58.159956"
        },
        {
          "url": "https://www.pbs.org/wgbh/nova/rss/nova-podcasts-rss.xml",
          "status": "success",
          "fetched_at": "2026-01-28T21:36:58.510397"
        },
        {
          "url": "https://rss.art19.com/climate-one",
          "status": "success",
          "fetched_at": "2026-01-28T21:36:58.687906"
        },
        {
          "url": "https://feeds.megaphone.fm/HSW9992617712",
          "status": "success",
          "fetched_at": "2026-01-28T21:36:59.183584"
        }
      ],
      "successful_fetches": 4,
      "failed_fetches": 0
    }
  },
  "fetch_summary": {
    "successful": 36,
    "failed": 0,
    "total_items": 356
  }
}