{
  "last_updated": "2026-02-21T04:41:39.403364",
  "total_categories": 6,
  "total_feeds": 36,
  "categories": {
    "environmental_news": {
      "feed_count": 7,
      "feeds": [
        {
          "url": "https://insideclimatenews.org/feed/",
          "status": "success",
          "fetched_at": "2026-02-21T04:41:39.702552"
        },
        {
          "url": "https://www.carbonbrief.org/feed/",
          "status": "success",
          "fetched_at": "2026-02-21T04:41:40.115289"
        },
        {
          "url": "https://www.theguardian.com/environment/climate-crisis/rss",
          "status": "success",
          "fetched_at": "2026-02-21T04:41:40.390991"
        },
        {
          "url": "https://grist.org/feed/",
          "status": "success",
          "fetched_at": "2026-02-21T04:41:40.802640"
        },
        {
          "url": "https://e360.yale.edu/feed/",
          "status": "success",
          "fetched_at": "2026-02-21T04:41:41.186534"
        },
        {
          "url": "https://climatecrisis.house.gov/rss.xml",
          "status": "success",
          "fetched_at": "2026-02-21T04:41:41.591716"
        },
        {
          "url": "https://www.climatechangenews.com/feed/",
          "status": "success",
          "fetched_at": "2026-02-21T04:41:44.157516"
        }
      ],
      "successful_fetches": 7,
      "failed_fetches": 0
    },
    "climate_science": {
      "feed_count": 7,
      "feeds": [
        {
          "url": "https://climate.nasa.gov/feed/",
          "status": "success",
          "fetched_at": "2026-02-21T04:41:44.744689"
        },
        {
          "url": "https://www.ipcc.ch/feed/",
          "status": "success",
          "fetched_at": "2026-02-21T04:41:46.144371"
        },
        {
          "url": "https://www.climate.gov/news-features/feed",
          "status": "success",
          "fetched_at": "2026-02-21T04:41:46.496511"
        },
        {
          "url": "https://www.nature.com/nclimate.rss",
          "status": "success",
          "fetched_at": "2026-02-21T04:41:46.560635"
        },
        {
          "url": "https://www.science.org/rss/news_current.xml",
          "status": "success",
          "fetched_at": "2026-02-21T04:41:46.780594"
        },
        {
          "url": "https://www.sciencedaily.com/rss/earth_climate/climate.xml",
          "status": "success",
          "fetched_at": "2026-02-21T04:41:47.078358"
        },
        {
          "url": "https://unfccc.int/news/rss.xml",
          "status": "success",
          "fetched_at": "2026-02-21T04:41:50.815441"
        }
      ],
      "successful_fetches": 7,
      "failed_fetches": 0
    },
    "research_papers": {
      "feed_count": 7,
      "feeds": [
        {
          "url": "https://www.pnas.org/action/showFeed?type=etoc&feed=rss&jc=pnas",
          "status": "success",
          "fetched_at": "2026-02-21T04:41:51.174551"
        },
        {
          "url": "https://agupubs.onlinelibrary.wiley.com/feed/19448007/most-recent",
          "status": "success",
          "fetched_at": "2026-02-21T04:41:51.430237"
        },
        {
          "url": "https://iopscience.iop.org/journal/rss/1748-9326",
          "status": "success",
          "fetched_at": "2026-02-21T04:41:52.139742"
        },
        {
          "url": "https://www.frontiersin.org/journals/climate/rss",
          "status": "success",
          "fetched_at": "2026-02-21T04:41:52.639180"
        },
        {
          "url": "https://journals.ametsoc.org/action/showFeed?type=etoc&feed=rss&jc=clim",
          "status": "success",
          "fetched_at": "2026-02-21T04:41:52.890069"
        },
        {
          "url": "https://www.nature.com/nclimate.rss",
          "status": "success",
          "fetched_at": "2026-02-21T04:41:52.945926"
        },
        {
          "url": "https://www.sciencedirect.com/journal/global-environmental-change/rss",
          "status": "success",
          "fetched_at": "2026-02-21T04:41:53.074633"
        }
      ],
      "successful_fetches": 7,
      "failed_fetches": 0
    },
    "social_impact": {
      "feed_count": 6,
      "feeds": [
        {
          "url": "https://www.climatemigration.org.uk/rss",
          "status": "success",
          "fetched_at": "2026-02-21T04:41:59.235302"
        },
        {
          "url": "https://ejfoundation.org/rss/climate",
          "status": "success",
          "fetched_at": "2026-02-21T04:41:59.783785"
        },
        {
          "url": "https://www.climaterealityproject.org/blog/rss.xml",
          "status": "success",
          "fetched_at": "2026-02-21T04:41:59.960438"
        },
        {
          "url": "https://www.wri.org/blog/rss.xml",
          "status": "success",
          "fetched_at": "2026-02-21T04:42:00.318932"
        },
        {
          "url": "https://www.sei.org/feed/",
          "status": "success",
          "fetched_at": "2026-02-21T04:42:01.921574"
        },
        {
          "url": "https://www.climatejusticealliance.org/feed/",
          "status": "success",
          "fetched_at": "2026-02-21T04:42:03.281324"
        }
      ],
      "successful_fetches": 6,
      "failed_fetches": 0
    },
    "extreme_weather": {
      "feed_count": 5,
      "feeds": [
        {
          "url": "https://www.wunderground.com/cat6/feed",
          "status": "success",
          "fetched_at": "2026-02-21T04:42:04.332123"
        },
        {
          "url": "https://www.climatesignals.org/rss.xml",
          "status": "success",
          "fetched_at": "2026-02-21T04:42:05.742658"
        },
        {
          "url": "https://www.preventionweb.net/english/professional/news/rss.php",
          "status": "success",
          "fetched_at": "2026-02-21T04:42:06.136376"
        },
        {
          "url": "https://phys.org/rss-feed/earth-sciences/earth-sciences-news/",
          "status": "success",
          "fetched_at": "2026-02-21T04:42:06.484439"
        },
        {
          "url": "https://floodlist.com/feed",
          "status": "success",
          "fetched_at": "2026-02-21T04:42:06.697830"
        }
      ],
      "successful_fetches": 5,
      "failed_fetches": 0
    },
    "media": {
      "feed_count": 4,
      "feeds": [
        {
          "url": "https://climatecrisis.house.gov/rss.xml",
          "status": "success",
          "fetched_at": "2026-02-21T04:42:07.045587"
        },
        {
          "url": "https://www.pbs.org/wgbh/nova/rss/nova-podcasts-rss.xml",
          "status": "success",
          "fetched_at": "2026-02-21T04:42:07.407433"
        },
        {
          "url": "https://rss.art19.com/climate-one",
          "status": "success",
          "fetched_at": "2026-02-21T04:42:07.543838"
        },
        {
          "url": "https://feeds.megaphone.fm/HSW9992617712",
          "status": "success",
          "fetched_at": "2026-02-21T04:42:08.128403"
        }
      ],
      "successful_fetches": 4,
      "failed_fetches": 0
    }
  },
  "fetch_summary": {
    "successful": 36,
    "failed": 0,
    "total_items": 354
  }
}