{
  "last_updated": "2025-11-03T22:24:04.562615",
  "total_categories": 6,
  "total_feeds": 36,
  "categories": {
    "environmental_news": {
      "feed_count": 7,
      "feeds": [
        {
          "url": "https://insideclimatenews.org/feed/",
          "status": "success",
          "fetched_at": "2025-11-03T22:24:04.895143"
        },
        {
          "url": "https://www.carbonbrief.org/feed/",
          "status": "success",
          "fetched_at": "2025-11-03T22:24:05.363386"
        },
        {
          "url": "https://www.theguardian.com/environment/climate-crisis/rss",
          "status": "success",
          "fetched_at": "2025-11-03T22:24:05.533232"
        },
        {
          "url": "https://grist.org/feed/",
          "status": "success",
          "fetched_at": "2025-11-03T22:24:05.822608"
        },
        {
          "url": "https://e360.yale.edu/feed/",
          "status": "success",
          "fetched_at": "2025-11-03T22:24:06.309997"
        },
        {
          "url": "https://climatecrisis.house.gov/rss.xml",
          "status": "success",
          "fetched_at": "2025-11-03T22:24:06.758908"
        },
        {
          "url": "https://www.climatechangenews.com/feed/",
          "status": "success",
          "fetched_at": "2025-11-03T22:24:08.964594"
        }
      ],
      "successful_fetches": 7,
      "failed_fetches": 0
    },
    "climate_science": {
      "feed_count": 7,
      "feeds": [
        {
          "url": "https://climate.nasa.gov/feed/",
          "status": "success",
          "fetched_at": "2025-11-03T22:24:09.936490"
        },
        {
          "url": "https://www.ipcc.ch/feed/",
          "status": "success",
          "fetched_at": "2025-11-03T22:24:11.289483"
        },
        {
          "url": "https://www.climate.gov/news-features/feed",
          "status": "success",
          "fetched_at": "2025-11-03T22:24:11.825676"
        },
        {
          "url": "https://www.nature.com/nclimate.rss",
          "status": "success",
          "fetched_at": "2025-11-03T22:24:12.072926"
        },
        {
          "url": "https://www.science.org/rss/news_current.xml",
          "status": "success",
          "fetched_at": "2025-11-03T22:24:12.239417"
        },
        {
          "url": "https://www.sciencedaily.com/rss/earth_climate/climate.xml",
          "status": "success",
          "fetched_at": "2025-11-03T22:24:12.480824"
        },
        {
          "url": "https://unfccc.int/news/rss.xml",
          "status": "failed",
          "fetched_at": "2025-11-03T22:24:33.269883"
        }
      ],
      "successful_fetches": 6,
      "failed_fetches": 1
    },
    "research_papers": {
      "feed_count": 7,
      "feeds": [
        {
          "url": "https://www.pnas.org/action/showFeed?type=etoc&feed=rss&jc=pnas",
          "status": "success",
          "fetched_at": "2025-11-03T22:24:33.554774"
        },
        {
          "url": "https://agupubs.onlinelibrary.wiley.com/feed/19448007/most-recent",
          "status": "success",
          "fetched_at": "2025-11-03T22:24:33.941172"
        },
        {
          "url": "https://iopscience.iop.org/journal/rss/1748-9326",
          "status": "success",
          "fetched_at": "2025-11-03T22:24:34.528299"
        },
        {
          "url": "https://www.frontiersin.org/journals/climate/rss",
          "status": "success",
          "fetched_at": "2025-11-03T22:24:35.032184"
        },
        {
          "url": "https://journals.ametsoc.org/action/showFeed?type=etoc&feed=rss&jc=clim",
          "status": "success",
          "fetched_at": "2025-11-03T22:24:35.269963"
        },
        {
          "url": "https://www.nature.com/nclimate.rss",
          "status": "success",
          "fetched_at": "2025-11-03T22:24:35.366785"
        },
        {
          "url": "https://www.sciencedirect.com/journal/global-environmental-change/rss",
          "status": "success",
          "fetched_at": "2025-11-03T22:24:35.788897"
        }
      ],
      "successful_fetches": 7,
      "failed_fetches": 0
    },
    "social_impact": {
      "feed_count": 6,
      "feeds": [
        {
          "url": "https://www.climatemigration.org.uk/rss",
          "status": "success",
          "fetched_at": "2025-11-03T22:24:46.695012"
        },
        {
          "url": "https://ejfoundation.org/rss/climate",
          "status": "success",
          "fetched_at": "2025-11-03T22:24:47.257176"
        },
        {
          "url": "https://www.climaterealityproject.org/blog/rss.xml",
          "status": "success",
          "fetched_at": "2025-11-03T22:24:47.594513"
        },
        {
          "url": "https://www.wri.org/blog/rss.xml",
          "status": "success",
          "fetched_at": "2025-11-03T22:24:49.792878"
        },
        {
          "url": "https://www.sei.org/feed/",
          "status": "success",
          "fetched_at": "2025-11-03T22:24:50.911441"
        },
        {
          "url": "https://www.climatejusticealliance.org/feed/",
          "status": "success",
          "fetched_at": "2025-11-03T22:24:52.147836"
        }
      ],
      "successful_fetches": 6,
      "failed_fetches": 0
    },
    "extreme_weather": {
      "feed_count": 5,
      "feeds": [
        {
          "url": "https://www.wunderground.com/cat6/feed",
          "status": "success",
          "fetched_at": "2025-11-03T22:24:52.880280"
        },
        {
          "url": "https://www.climatesignals.org/rss.xml",
          "status": "success",
          "fetched_at": "2025-11-03T22:24:54.081129"
        },
        {
          "url": "https://www.preventionweb.net/english/professional/news/rss.php",
          "status": "success",
          "fetched_at": "2025-11-03T22:24:54.530560"
        },
        {
          "url": "https://phys.org/rss-feed/earth-sciences/earth-sciences-news/",
          "status": "success",
          "fetched_at": "2025-11-03T22:24:54.867063"
        },
        {
          "url": "https://floodlist.com/feed",
          "status": "success",
          "fetched_at": "2025-11-03T22:24:55.133478"
        }
      ],
      "successful_fetches": 5,
      "failed_fetches": 0
    },
    "media": {
      "feed_count": 4,
      "feeds": [
        {
          "url": "https://climatecrisis.house.gov/rss.xml",
          "status": "success",
          "fetched_at": "2025-11-03T22:24:55.584976"
        },
        {
          "url": "https://www.pbs.org/wgbh/nova/rss/nova-podcasts-rss.xml",
          "status": "success",
          "fetched_at": "2025-11-03T22:24:55.947985"
        },
        {
          "url": "https://rss.art19.com/climate-one",
          "status": "success",
          "fetched_at": "2025-11-03T22:24:56.300202"
        },
        {
          "url": "https://feeds.megaphone.fm/HSW9992617712",
          "status": "success",
          "fetched_at": "2025-11-03T22:24:56.798013"
        }
      ],
      "successful_fetches": 4,
      "failed_fetches": 0
    }
  },
  "fetch_summary": {
    "successful": 35,
    "failed": 1,
    "total_items": 351
  }
}